{"user": [{"username": "John", "email": "john@haha.com", "password": "Hahaha123", "fullname": "John rukmana"}, {"username": "jeff", "email": "jeff@haha.com", "password": "Hahaha123", "fullname": "John rukmana"}, {"username": "hikmat", "email": "hikmat@gmail.com", "password": "kumiskucing", "fullname": "oka aryanata"}, {"username": "oka", "email": "oka@gmail.com", "password": "kumiskucing", "fullname": "oka aryanata"}], "tweet": [{"email": "hikmat@gmail.com", "tweet": "oka", "time": "2018-10-17 14:52:48.763654"}, {"email": "oka@gmail.com", "tweet": "ako", "time": "2018-10-17 15:00:37.152886"}]}